LICENSE
MANIFEST.in
README.md
setup.py
relay/__init__.py
relay/__main__.py
relay/argparse_shared.py
relay/relay_logging.py
relay/runner.py
relay/util.py
relay.runner.egg-info/PKG-INFO
relay.runner.egg-info/SOURCES.txt
relay.runner.egg-info/dependency_links.txt
relay.runner.egg-info/entry_points.txt
relay.runner.egg-info/requires.txt
relay.runner.egg-info/top_level.txt
relay.runner.egg-info/zip-safe
relay/plugins/__init__.py