Metadata-Version: 1.0
Name: relay.runner
Version: 0.1.9
Summary: A smart thermostat.  Given a metric, or some timeseries that should approach a given target, add heat or coolant as necessary You can use Relay to auto-scale workers in large distributed systems or do anything a thermostat might do.
Home-page: http://github.com/sailthru/relay
Author: Alex Gaudio
Author-email: adgaudio@gmail.com
License: UNKNOWN
Keywords: relay,pid,pid controller,thermostat,tuning,oscilloscope,auto-scale
Platform: UNKNOWN
